pixel_ring/__init__.py
pixel_ring/apa102.py
pixel_ring/apa102_pixel_ring.py
pixel_ring/pattern.py
pixel_ring/usb_pixel_ring_v1.py
pixel_ring/usb_pixel_ring_v2.py
pixel_ring-0.0.6.dist-info/DESCRIPTION.rst
pixel_ring-0.0.6.dist-info/METADATA
pixel_ring-0.0.6.dist-info/RECORD
pixel_ring-0.0.6.dist-info/WHEEL
pixel_ring-0.0.6.dist-info/entry_points.txt
pixel_ring-0.0.6.dist-info/metadata.json
pixel_ring-0.0.6.dist-info/top_level.txt
